generate_img_with_sber/__init__.py
generate_img_with_sber/generateimgsber.py
generate_img_with_sber-0.0.1.dist-info/METADATA
generate_img_with_sber-0.0.1.dist-info/WHEEL
generate_img_with_sber-0.0.1.dist-info/top_level.txt
generate_img_with_sber-0.0.1.dist-info/RECORD
