Metadata-Version: 2.1
Name: generate_img_with_sber
Version: 0.0.1
Summary: This is simple library for generating images using the Kavinsky neural network
Home-page: https://github.com/Ivango128/generate_img_with_sber
Author: Ivango128
Author-email: poplayhin2002@gmail.com
Project-URL: GitHub, https://github.com/Ivango128/generate_img_with_sber
Keywords: generate pictures
Classifier: Programming Language :: Python :: 3.11
Classifier: License :: OSI Approved :: MIT License
Classifier: Operating System :: OS Independent
Requires-Python: >=3.6
Requires-Dist: requests
